ahvac/__init__.py
ahvac/api_client.py
ahvac/api_response.py
ahvac/configuration.py
ahvac/exceptions.py
ahvac/py.typed
ahvac/rest.py
ahvac/api/__init__.py
ahvac/api/auth_api.py
ahvac/api/identity_api.py
ahvac/api/secrets_api.py
ahvac/api/system_api.py
ahvac/models/__init__.py
ahvac/models/ali_cloud_configure_request.py
ahvac/models/ali_cloud_login_request.py
ahvac/models/ali_cloud_write_auth_role_request.py
ahvac/models/ali_cloud_write_role_request.py
ahvac/models/alias_create_request.py
ahvac/models/alias_update_by_id_request.py
ahvac/models/app_role_destroy_secret_id_by_accessor_request.py
ahvac/models/app_role_destroy_secret_id_request.py
ahvac/models/app_role_login_request.py
ahvac/models/app_role_login_response.py
ahvac/models/app_role_look_up_secret_id_by_accessor_request.py
ahvac/models/app_role_look_up_secret_id_by_accessor_response.py
ahvac/models/app_role_look_up_secret_id_request.py
ahvac/models/app_role_look_up_secret_id_response.py
ahvac/models/app_role_read_bind_secret_id_response.py
ahvac/models/app_role_read_bound_cidr_list_response.py
ahvac/models/app_role_read_local_secret_ids_response.py
ahvac/models/app_role_read_period_response.py
ahvac/models/app_role_read_policies_response.py
ahvac/models/app_role_read_role_id_response.py
ahvac/models/app_role_read_role_response.py
ahvac/models/app_role_read_secret_id_bound_cidrs_response.py
ahvac/models/app_role_read_secret_id_num_uses_response.py
ahvac/models/app_role_read_secret_id_ttl_response.py
ahvac/models/app_role_read_token_bound_cidrs_response.py
ahvac/models/app_role_read_token_max_ttl_response.py
ahvac/models/app_role_read_token_num_uses_response.py
ahvac/models/app_role_read_token_ttl_response.py
ahvac/models/app_role_write_bind_secret_id_request.py
ahvac/models/app_role_write_bound_cidr_list_request.py
ahvac/models/app_role_write_custom_secret_id_request.py
ahvac/models/app_role_write_custom_secret_id_response.py
ahvac/models/app_role_write_period_request.py
ahvac-1.15.0.dist-info/LICENSE
ahvac-1.15.0.dist-info/METADATA
ahvac-1.15.0.dist-info/WHEEL
ahvac-1.15.0.dist-info/top_level.txt
ahvac-1.15.0.dist-info/RECORD
