Metadata-Version: 2.1
Name: ahvac
Version: 1.15.0
Summary: HashiCorp Vault Python async client
Home-page: https://github.com/r00ta/ahvac
Author: Jacopo Rota
Author-email: jacopo.r00ta@gmail.com
License: Apache License Version 2.0
Keywords: OpenAPI,OpenAPI-Generator,HashiCorp Vault API
License-File: LICENSE
Requires-Dist: urllib3 <2.1.0,>=1.25.3
Requires-Dist: python-dateutil
Requires-Dist: aiohttp >=3.0.0
Requires-Dist: aiohttp-retry >=2.8.3
Requires-Dist: pydantic >=2
Requires-Dist: typing-extensions >=4.7.1
